{
    "urls": [
        {
            "name": "🍚饭太硬",
            "url": "http://www.饭太硬.com/tv"
        },
        {
            "name": "🐼肥猫",
            "url": "http://肥猫.com/"
        },
        {
            "name": "喵影视",
            "url": "http://meowtv.top/tv"
        },
        {
            "name": "🐶OK猫接口",
            "url": "http://ok321.top/ok"
        },
        {
            "name": "🐹老猫迷接口",
            "url": "https://d.n13.club/"
        },
        {
            "name": "科技长青",
            "url": "http://yuan.haitangw.net/tv/"
        },
        {
            "name": "🐎小马接口",
            "url": "https://szyyds.cn/tv/x.json"
        },
        {
            "name": "七星",
            "url": "https://tvkj.top/tw/api.json"
        },
        {
            "name": "小盒子",
            "url": "http://xhztv.top/xhz"
        },
        {
            "name": "小盒子4k",
            "url": "http://xhztv.top/4k.json"
        },
        {
            "name": "💝恋影",
            "url": "https://www.lianyingtv.com/fast/fast"
        },
        {
            "name": "💦巧技",
            "url": "https://pandown.pro/tvbox/tvbox.json"
        },
        {
            "name": "🚒运输车接口",
            "url": "https://cf.weixine.net/ysc.json"
        },
        {
            "name": "🍔挺好分享源",
            "url": "http://ztha.top/TVBox/thdjk.json"
        },
        {
            "name": "🧙‍♀️老刘备接口",
            "url": "https://raw.liucn.cc/box/m.json"
        },
        {
            "name": "🐙动漫主接口",
            "url": "https://www.yingm.cc/dm/dm.json"
        },
        {
            "name": "🐠摸鱼接口",
            "url": "http://www.wya6.cn/tv/yc.php"
        },
        {
            "name": "Nice",
            "url": "https://NiceZoneCoder.github.io/tvbox.json"
        }
    ]
}
